kingjimin/__init__.py
kingjimin/data.py
kingjimin/kingjimin.py
kingjimin-2.2.5.dist-info/METADATA
kingjimin-2.2.5.dist-info/WHEEL
kingjimin-2.2.5.dist-info/top_level.txt
kingjimin-2.2.5.dist-info/RECORD
