Metadata-Version: 2.1
Name: kingjimin
Version: 2.2.5
Summary: Test Package
Author: jiminlee
Author-email: jimin.lee@nota.ai
License: UNKNOWN
Platform: UNKNOWN
Requires-Python: >=3
Requires-Dist: requests
Requires-Dist: contextlib2
Requires-Dist: polling2
Requires-Dist: urllib3
Requires-Dist: multipledispatch
Requires-Dist: mock
